Workbook

Sheet Sales Data
A1: 🏆 SALES DATA ANALYSIS | FY 2024
A2: Order ID | B2: Date | C2: Salesperson | D2: Region | E2: Product | F2: Category | G2: Units Sold | H2: Unit Price ($) | I2: Revenue ($) | J2: Profit ($)
A3: ORD-1001 | B3: 2024-01-08 | C3: Alice Johnson | D3: North | E3: Training | F3: Services | G3: 8 | H3: 200 | I3: 1600 | J3: 800
A4: ORD-1002 | B4: 2024-01-03 | C4: Carol White | D4: South | E4: Support Plan | F4: Services | G4: 18 | H4: 100 | I4: 1800 | J4: 810
A5: ORD-1003 | B5: 2024-01-08 | C5: Grace Kim | D5: West | E5: Laptop | F5: Electronics | G5: 7 | H5: 850 | I5: 5950 | J5: 1309
A6: ORD-1004 | B6: 2024-01-14 | C6: Alice Johnson | D6: North | E6: Support Plan | F6: Services | G6: 18 | H6: 100 | I6: 1800 | J6: 810
A7: ORD-1005 | B7: 2024-01-25 | C7: David Brown | D7: South | E7: Training | F7: Services | G7: 1 | H7: 200 | I7: 200 | J7: 100
A8: ORD-1006 | B8: 2024-01-07 | C8: David Brown | D8: South | E8: Analytics Pro | F8: Software | G8: 5 | H8: 800 | I8: 4000 | J8: 2600
A9: ORD-1007 | B9: 2024-01-12 | C9: Eva Martinez | D9: East | E9: Tablet | F9: Electronics | G9: 4 | H9: 320 | I9: 1280 | J9: 358.4
A10: ORD-1008 | B10: 2024-01-18 | C10: Frank Lee | D10: East | E10: Headphones | F10: Electronics | G10: 15 | H10: 75 | I10: 1125 | J10: 450
A11: ORD-1009 | B11: 2024-01-27 | C11: Bob Smith | D11: North | E11: Headphones | F11: Electronics | G11: 10 | H11: 75 | I11: 750 | J11: 300
A12: ORD-1010 | B12: 2024-01-22 | C12: Eva Martinez | D12: East | E12: Consulting | F12: Services | G12: 2 | H12: 150 | I12: 300 | J12: 165
A13: ORD-1011 | B13: 2024-01-13 | C13: David Brown | D13: South | E13: Laptop | F13: Electronics | G13: 4 | H13: 850 | I13: 3400 | J13: 748
A14: ORD-1012 | B14: 2024-01-12 | C14: Frank Lee | D14: East | E14: Training | F14: Services | G14: 6 | H14: 200 | I14: 1200 | J14: 600
... A146: ORD-1144 | B146: 2024-12-03 | C146: Alice Johnson | D146: North | E146: Laptop | F146: Electronics | G146: 18 | H146: 850 | I146: 15300 | J146: 3366
A147: TOTALS | G147: =SUM(G3:G146) -> 1550 | I147: =SUM(I3:I146) -> 721030 | J147: =SUM(J3:J146) -> 374692.4

Sheet Summary Dashboard
A1: 📊 EXECUTIVE SUMMARY DASHBOARD | FY 2024
A3: Total Revenue ($) | C3: Total Profit ($) | E3: Total Orders | G3: Total Units Sold | I3: Avg Order Revenue ($) | K3: Profit Margin (%)
A4: ='Sales Data'!I147 -> 721030 | C4: ='Sales Data'!J147 -> 374692.4 | E4: =COUNTA('Sales Data'!A3:A146) -> 144 | G4: ='Sales Data'!G147 -> 1550 | I4: =A4/E4 -> 5007.1528 | K4: =C4/A4 -> 0.5196627
A8: Monthly Revenue & Profit | G8: Revenue by Region
A9: Month | B9: Revenue ($) | C9: Profit ($) | D9: Units | E9: Orders | G9: Region | H9: Revenue ($) | I9: Profit ($) | J9: Orders
A10: Jan | B10: =SUMPRODUCT(('Sales Data'!B3:B146>="2024-01-01")*('Sales Data'!B3:B146<"2024-01-32")*'Sales Data'!I3:I146) -> 24005 | C10: =SUMPRODUCT(('Sales Data'!B3:B146>="2024-01-01")*('Sales Data'!B3:B146<"2024-01-32")*'Sales Data'!J3:J146) -> 9350.4 | D10: =SUMPRODUCT(('Sales Data'!B3:B146>="2024-01-01")*('Sales Data'!B3:B146<"2024-01-32")*'Sales Data'!G3:G146) -> 101 | E10: =SUMPRODUCT(('Sales Data'!B3:B146>="2024-01-01")*('Sales Data'!B3:B146<"2024-01-32")*1) -> 13 | G10: North | H10: =SUMPRODUCT(('Sales Data'!D3:D146="North")*'Sales Data'!I3:I146) -> 274895 | I10: =SUMPRODUCT(('Sales Data'!D3:D146="North")*'Sales Data'!J3:J146) -> 142171.1 | J10: =COUNTIF('Sales Data'!D3:D146,"North") -> 36
A11: Feb | B11: =SUMPRODUCT(('Sales Data'!B3:B146>="2024-02-01")*('Sales Data'!B3:B146<"2024-02-32")*'Sales Data'!I3:I146) -> 65190 | C11: =SUMPRODUCT(('Sales Data'!B3:B146>="2024-02-01")*('Sales Data'!B3:B146<"2024-02-32")*'Sales Data'!J3:J146) -> 37268.7 | D11: =SUMPRODUCT(('Sales Data'!B3:B146>="2024-02-01")*('Sales Data'!B3:B146<"2024-02-32")*'Sales Data'!G3:G146) -> 134 | E11: =SUMPRODUCT(('Sales Data'!B3:B146>="2024-02-01")*('Sales Data'!B3:B146<"2024-02-32")*1) -> 13 | G11: South | H11: =SUMPRODUCT(('Sales Data'!D3:D146="South")*'Sales Data'!I3:I146) -> 159670 | I11: =SUMPRODUCT(('Sales Data'!D3:D146="South")*'Sales Data'!J3:J146) -> 87206.6 | J11: =COUNTIF('Sales Data'!D3:D146,"South") -> 40
A12: Mar | B12: =SUMPRODUCT(('Sales Data'!B3:B146>="2024-03-01")*('Sales Data'!B3:B146<"2024-03-32")*'Sales Data'!I3:I146) -> 95800 | C12: =SUMPRODUCT(('Sales Data'!B3:B146>="2024-03-01")*('Sales Data'!B3:B146<"2024-03-32")*'Sales Data'!J3:J146) -> 55847 | D12: =SUMPRODUCT(('Sales Data'!B3:B146>="2024-03-01")*('Sales Data'!B3:B146<"2024-03-32")*'Sales Data'!G3:G146) -> 129 | E12: =SUMPRODUCT(('Sales Data'!B3:B146>="2024-03-01")*('Sales Data'!B3:B146<"2024-03-32")*1) -> 12 | G12: East | H12: =SUMPRODUCT(('Sales Data'!D3:D146="East")*'Sales Data'!I3:I146) -> 127935 | I12: =SUMPRODUCT(('Sales Data'!D3:D146="East")*'Sales Data'!J3:J146) -> 62176.3 | J12: =COUNTIF('Sales Data'!D3:D146,"East") -> 37
A13: Apr | B13: =SUMPRODUCT(('Sales Data'!B3:B146>="2024-04-01")*('Sales Data'!B3:B146<"2024-04-32")*'Sales Data'!I3:I146) -> 103235 | C13: =SUMPRODUCT(('Sales Data'!B3:B146>="2024-04-01")*('Sales Data'!B3:B146<"2024-04-32")*'Sales Data'!J3:J146) -> 45113.8 | D13: =SUMPRODUCT(('Sales Data'!B3:B146>="2024-04-01")*('Sales Data'!B3:B146<"2024-04-32")*'Sales Data'!G3:G146) -> 167 | E13: =SUMPRODUCT(('Sales Data'!B3:B146>="2024-04-01")*('Sales Data'!B3:B146<"2024-04-32")*1) -> 14 | G13: West | H13: =SUMPRODUCT(('Sales Data'!D3:D146="West")*'Sales Data'!I3:I146) -> 158530 | I13: =SUMPRODUCT(('Sales Data'!D3:D146="West")*'Sales Data'!J3:J146) -> 83138.4 | J13: =COUNTIF('Sales Data'!D3:D146,"West") -> 31
A14: May | B14: =SUMPRODUCT(('Sales Data'!B3:B146>="2024-05-01")*('Sales Data'!B3:B146<"2024-05-32")*'Sales Data'!I3:I146) -> 41300 | C14: =SUMPRODUCT(('Sales Data'!B3:B146>="2024-05-01")*('Sales Data'!B3:B146<"2024-05-32")*'Sales Data'!J3:J146) -> 19721 | D14: =SUMPRODUCT(('Sales Data'!B3:B146>="2024-05-01")*('Sales Data'!B3:B146<"2024-05-32")*'Sales Data'!G3:G146) -> 97 | E14: =SUMPRODUCT(('Sales Data'!B3:B146>="2024-05-01")*('Sales Data'!B3:B146<"2024-05-32")*1) -> 10 | G14: TOTAL | H14: =SUM(H10:H13) -> 721030 | I14: =SUM(I10:I13) -> 374692.4 | J14: =SUM(J10:J13) -> 144
A15: Jun | B15: =SUMPRODUCT(('Sales Data'!B3:B146>="2024-06-01")*('Sales Data'!B3:B146<"2024-06-32")*'Sales Data'!I3:I146) -> 42665 | C15: =SUMPRODUCT(('Sales Data'!B3:B146>="2024-06-01")*('Sales Data'!B3:B146<"2024-06-32")*'Sales Data'!J3:J146) -> 11919.2 | D15: =SUMPRODUCT(('Sales Data'!B3:B146>="2024-06-01")*('Sales Data'!B3:B146<"2024-06-32")*'Sales Data'!G3:G146) -> 91 | E15: =SUMPRODUCT(('Sales Data'!B3:B146>="2024-06-01")*('Sales Data'!B3:B146<"2024-06-32")*1) -> 11
A16: Jul | B16: =SUMPRODUCT(('Sales Data'!B3:B146>="2024-07-01")*('Sales Data'!B3:B146<"2024-07-32")*'Sales Data'!I3:I146) -> 46750 | C16: =SUMPRODUCT(('Sales Data'!B3:B146>="2024-07-01")*('Sales Data'!B3:B146<"2024-07-32")*'Sales Data'!J3:J146) -> 28605 | D16: =SUMPRODUCT(('Sales Data'!B3:B146>="2024-07-01")*('Sales Data'!B3:B146<"2024-07-32")*'Sales Data'!G3:G146) -> 131 | E16: =SUMPRODUCT(('Sales Data'!B3:B146>="2024-07-01")*('Sales Data'!B3:B146<"2024-07-32")*1) -> 12 | G16: Revenue by Category
A17: Aug | B17: =SUMPRODUCT(('Sales Data'!B3:B146>="2024-08-01")*('Sales Data'!B3:B146<"2024-08-32")*'Sales Data'!I3:I146) -> 62600 | C17: =SUMPRODUCT(('Sales Data'!B3:B146>="2024-08-01")*('Sales Data'!B3:B146<"2024-08-32")*'Sales Data'!J3:J146) -> 35791 | D17: =SUMPRODUCT(('Sales Data'!B3:B146>="2024-08-01")*('Sales Data'!B3:B146<"2024-08-32")*'Sales Data'!G3:G146) -> 154 | E17: =SUMPRODUCT(('Sales Data'!B3:B146>="2024-08-01")*('Sales Data'!B3:B146<"2024-08-32")*1) -> 14 | G17: Category | H17: Revenue ($) | I17: Profit ($) | J17: Units
A18: Sep | B18: =SUMPRODUCT(('Sales Data'!B3:B146>="2024-09-01")*('Sales Data'!B3:B146<"2024-09-32")*'Sales Data'!I3:I146) -> 32290 | C18: =SUMPRODUCT(('Sales Data'!B3:B146>="2024-09-01")*('Sales Data'!B3:B146<"2024-09-32")*'Sales Data'!J3:J146) -> 15355.2 | D18: =SUMPRODUCT(('Sales Data'!B3:B146>="2024-09-01")*('Sales Data'!B3:B146<"2024-09-32")*'Sales Data'!G3:G146) -> 113 | E18: =SUMPRODUCT(('Sales Data'!B3:B146>="2024-09-01")*('Sales Data'!B3:B146<"2024-09-32")*1) -> 8 | G18: Electronics | H18: =SUMPRODUCT(('Sales Data'!F3:F146="Electronics")*'Sales Data'!I3:I146) -> 226030 | I18: =SUMPRODUCT(('Sales Data'!F3:F146="Electronics")*'Sales Data'!J3:J146) -> 56037.4 | J18: =SUMPRODUCT(('Sales Data'!F3:F146="Electronics")*'Sales Data'!G3:G146) -> 575
A19: Oct | B19: =SUMPRODUCT(('Sales Data'!B3:B146>="2024-10-01")*('Sales Data'!B3:B146<"2024-10-32")*'Sales Data'!I3:I146) -> 86665 | C19: =SUMPRODUCT(('Sales Data'!B3:B146>="2024-10-01")*('Sales Data'!B3:B146<"2024-10-32")*'Sales Data'!J3:J146) -> 52629.2 | D19: =SUMPRODUCT(('Sales Data'!B3:B146>="2024-10-01")*('Sales Data'!B3:B146<"2024-10-32")*'Sales Data'!G3:G146) -> 155 | E19: =SUMPRODUCT(('Sales Data'!B3:B146>="2024-10-01")*('Sales Data'!B3:B146<"2024-10-32")*1) -> 14 | G19: Software | H19: =SUMPRODUCT(('Sales Data'!F3:F146="Software")*'Sales Data'!I3:I146) -> 423300 | I19: =SUMPRODUCT(('Sales Data'!F3:F146="Software")*'Sales Data'!J3:J146) -> 283140 | J19: =SUMPRODUCT(('Sales Data'!F3:F146="Software")*'Sales Data'!G3:G146) -> 509
A20: Nov | B20: =SUMPRODUCT(('Sales Data'!B3:B146>="2024-11-01")*('Sales Data'!B3:B146<"2024-11-32")*'Sales Data'!I3:I146) -> 82660 | C20: =SUMPRODUCT(('Sales Data'!B3:B146>="2024-11-01")*('Sales Data'!B3:B146<"2024-11-32")*'Sales Data'!J3:J146) -> 47979.8 | D20: =SUMPRODUCT(('Sales Data'!B3:B146>="2024-11-01")*('Sales Data'!B3:B146<"2024-11-32")*'Sales Data'!G3:G146) -> 181 | E20: =SUMPRODUCT(('Sales Data'!B3:B146>="2024-11-01")*('Sales Data'!B3:B146<"2024-11-32")*1) -> 14 | G20: Services | H20: =SUMPRODUCT(('Sales Data'!F3:F146="Services")*'Sales Data'!I3:I146) -> 71700 | I20: =SUMPRODUCT(('Sales Data'!F3:F146="Services")*'Sales Data'!J3:J146) -> 35515 | J20: =SUMPRODUCT(('Sales Data'!F3:F146="Services")*'Sales Data'!G3:G146) -> 466
A21: Dec | B21: =SUMPRODUCT(('Sales Data'!B3:B146>="2024-12-01")*('Sales Data'!B3:B146<"2024-12-32")*'Sales Data'!I3:I146) -> 37870 | C21: =SUMPRODUCT(('Sales Data'!B3:B146>="2024-12-01")*('Sales Data'!B3:B146<"2024-12-32")*'Sales Data'!J3:J146) -> 15112.1 | D21: =SUMPRODUCT(('Sales Data'!B3:B146>="2024-12-01")*('Sales Data'!B3:B146<"2024-12-32")*'Sales Data'!G3:G146) -> 97 | E21: =SUMPRODUCT(('Sales Data'!B3:B146>="2024-12-01")*('Sales Data'!B3:B146<"2024-12-32")*1) -> 9
A22: TOTAL | B22: =SUM(B10:B21) -> 721030 | C22: =SUM(C10:C21) -> 374692.4 | D22: =SUM(D10:D21) -> 1550 | E22: =SUM(E10:E21) -> 144

Sheet Charts
A1: 📈 VISUAL ANALYTICS | FY 2024

Sheet Leaderboard
A1: 🥇 SALESPERSON LEADERBOARD | FY 2024
A2: Rank | B2: Salesperson | C2: Region | D2: Revenue ($) | E2: Profit ($) | F2: Orders
A3: 🥇 1st | B3: Alice Johnson | C3: North | D3: =SUMPRODUCT(('Sales Data'!C3:C146="Alice Johnson")*'Sales Data'!I3:I146) -> 205445 | E3: =SUMPRODUCT(('Sales Data'!C3:C146="Alice Johnson")*'Sales Data'!J3:J146) -> 110403.1 | F3: =COUNTIF('Sales Data'!C3:C146,"Alice Johnson") -> 24
A4: 🥈 2nd | B4: Bob Smith | C4: North | D4: =SUMPRODUCT(('Sales Data'!C3:C146="Bob Smith")*'Sales Data'!I3:I146) -> 69450 | E4: =SUMPRODUCT(('Sales Data'!C3:C146="Bob Smith")*'Sales Data'!J3:J146) -> 31768 | F4: =COUNTIF('Sales Data'!C3:C146,"Bob Smith") -> 12
A5: 🥉 3rd | B5: Carol White | C5: South | D5: =SUMPRODUCT(('Sales Data'!C3:C146="Carol White")*'Sales Data'!I3:I146) -> 85490 | E5: =SUMPRODUCT(('Sales Data'!C3:C146="Carol White")*'Sales Data'!J3:J146) -> 48798.2 | F5: =COUNTIF('Sales Data'!C3:C146,"Carol White") -> 16
A6: #4 | B6: David Brown | C6: South | D6: =SUMPRODUCT(('Sales Data'!C3:C146="David Brown")*'Sales Data'!I3:I146) -> 74180 | E6: =SUMPRODUCT(('Sales Data'!C3:C146="David Brown")*'Sales Data'!J3:J146) -> 38408.4 | F6: =COUNTIF('Sales Data'!C3:C146,"David Brown") -> 24
A7: #5 | B7: Eva Martinez | C7: East | D7: =SUMPRODUCT(('Sales Data'!C3:C146="Eva Martinez")*'Sales Data'!I3:I146) -> 71790 | E7: =SUMPRODUCT(('Sales Data'!C3:C146="Eva Martinez")*'Sales Data'!J3:J146) -> 30844.2 | F7: =COUNTIF('Sales Data'!C3:C146,"Eva Martinez") -> 19
A8: #6 | B8: Frank Lee | C8: East | D8: =SUMPRODUCT(('Sales Data'!C3:C146="Frank Lee")*'Sales Data'!I3:I146) -> 56145 | E8: =SUMPRODUCT(('Sales Data'!C3:C146="Frank Lee")*'Sales Data'!J3:J146) -> 31332.1 | F8: =COUNTIF('Sales Data'!C3:C146,"Frank Lee") -> 18
A9: #7 | B9: Grace Kim | C9: West | D9: =SUMPRODUCT(('Sales Data'!C3:C146="Grace Kim")*'Sales Data'!I3:I146) -> 83770 | E9: =SUMPRODUCT(('Sales Data'!C3:C146="Grace Kim")*'Sales Data'!J3:J146) -> 45316.6 | F9: =COUNTIF('Sales Data'!C3:C146,"Grace Kim") -> 17
A10: #8 | B10: Henry Davis | C10: West | D10: =SUMPRODUCT(('Sales Data'!C3:C146="Henry Davis")*'Sales Data'!I3:I146) -> 74760 | E10: =SUMPRODUCT(('Sales Data'!C3:C146="Henry Davis")*'Sales Data'!J3:J146) -> 37821.8 | F10: =COUNTIF('Sales Data'!C3:C146,"Henry Davis") -> 14
